cellmate/__init__.py
cellmate/components.py
cellmate/errors.py
cellmate/styles.py
cellmate-0.2.0.dist-info/licenses/LICENSE
tests/__init__.py
tests/test_cellmate.py
cellmate-0.2.0.dist-info/METADATA
cellmate-0.2.0.dist-info/WHEEL
cellmate-0.2.0.dist-info/top_level.txt
cellmate-0.2.0.dist-info/RECORD
